simplemma/__init__.py
simplemma/__metadata__.py
simplemma/language_detector.py
simplemma/lemmatizer.py
simplemma/py.typed
simplemma/token_sampler.py
simplemma/tokenizer.py
simplemma/utils.py
simplemma/strategies/__init__.py
simplemma/strategies/affix_decomposition.py
simplemma/strategies/default.py
simplemma/strategies/dictionary_lookup.py
simplemma/strategies/greedy_dictionary_lookup.py
simplemma/strategies/hyphen_removal.py
simplemma/strategies/lemmatization_strategy.py
simplemma/strategies/prefix_decomposition.py
simplemma/strategies/rules.py
simplemma/strategies/defaultprefixes/__init__.py
simplemma/strategies/defaultprefixes/de.py
simplemma/strategies/defaultprefixes/ru.py
simplemma/strategies/defaultrules/__init__.py
simplemma/strategies/defaultrules/de.py
simplemma/strategies/defaultrules/en.py
simplemma/strategies/defaultrules/et.py
simplemma/strategies/defaultrules/fi.py
simplemma/strategies/defaultrules/generic.py
simplemma/strategies/defaultrules/lv.py
simplemma/strategies/defaultrules/nl.py
simplemma/strategies/defaultrules/pl.py
simplemma/strategies/defaultrules/ru.py
simplemma/strategies/dictionaries/__init__.py
simplemma/strategies/dictionaries/dictionary_factory.py
simplemma/strategies/dictionaries/trie_directory_factory.py
simplemma/strategies/dictionaries/data/ast.plzma
simplemma/strategies/dictionaries/data/bg.plzma
simplemma/strategies/dictionaries/data/ca.plzma
simplemma/strategies/dictionaries/data/cs.plzma
simplemma/strategies/dictionaries/data/cy.plzma
simplemma/strategies/dictionaries/data/da.plzma
simplemma/strategies/dictionaries/data/de.plzma
simplemma/strategies/dictionaries/data/el.plzma
simplemma/strategies/dictionaries/data/en.plzma
simplemma/strategies/dictionaries/data/enm.plzma
simplemma/strategies/dictionaries/data/es.plzma
simplemma/strategies/dictionaries/data/et.plzma
simplemma/strategies/dictionaries/data/fa.plzma
simplemma/strategies/dictionaries/data/fi.plzma
simplemma/strategies/dictionaries/data/fr.plzma
simplemma-1.1.2.dist-info/LICENSE
simplemma-1.1.2.dist-info/METADATA
simplemma-1.1.2.dist-info/WHEEL
simplemma-1.1.2.dist-info/top_level.txt
simplemma-1.1.2.dist-info/RECORD
