Metadata-Version: 2.1
Name: simplemma
Version: 1.1.2
Summary: A lightweight toolkit for multilingual lemmatization and language detection.
Author-email: Adrien Barbaresi <barbaresi@bbaw.de>
License: MIT License
Project-URL: Homepage, https://github.com/adbar/simplemma
Project-URL: Docs, https://adbar.github.io/simplemma/
Project-URL: Blog, https://adrien.barbaresi.eu/blog/
Keywords: language detection,language identification,langid,lemmatization,lemmatizer,lemmatiser,nlp,tokenization,tokenizer
Classifier: Development Status :: 4 - Beta
Classifier: Intended Audience :: Developers
Classifier: Intended Audience :: Education
Classifier: Intended Audience :: Information Technology
Classifier: Intended Audience :: Science/Research
Classifier: License :: OSI Approved :: MIT License
Classifier: Natural Language :: Bulgarian
Classifier: Natural Language :: Catalan
Classifier: Natural Language :: Croatian
Classifier: Natural Language :: Czech
Classifier: Natural Language :: Danish
Classifier: Natural Language :: Dutch
Classifier: Natural Language :: English
Classifier: Natural Language :: Finnish
Classifier: Natural Language :: French
Classifier: Natural Language :: Galician
Classifier: Natural Language :: German
Classifier: Natural Language :: Greek
Classifier: Natural Language :: Hindi
Classifier: Natural Language :: Hungarian
Classifier: Natural Language :: Icelandic
Classifier: Natural Language :: Indonesian
Classifier: Natural Language :: Irish
Classifier: Natural Language :: Italian
Classifier: Natural Language :: Latin
Classifier: Natural Language :: Latvian
Classifier: Natural Language :: Lithuanian
Classifier: Natural Language :: Macedonian
Classifier: Natural Language :: Malay
Classifier: Natural Language :: Norwegian
Classifier: Natural Language :: Polish
Classifier: Natural Language :: Portuguese
Classifier: Natural Language :: Romanian
Classifier: Natural Language :: Russian
Classifier: Natural Language :: Slovak
Classifier: Natural Language :: Slovenian
Classifier: Natural Language :: Spanish
Classifier: Natural Language :: Swedish
Classifier: Natural Language :: Thai
Classifier: Natural Language :: Turkish
Classifier: Natural Language :: Ukrainian
Classifier: Operating System :: OS Independent
Classifier: Programming Language :: Python :: 3
Classifier: Programming Language :: Python :: 3.8
Classifier: Programming Language :: Python :: 3.9
Classifier: Programming Language :: Python :: 3.10
Classifier: Programming Language :: Python :: 3.11
Classifier: Programming Language :: Python :: 3.12
Classifier: Programming Language :: Python :: 3.13
Classifier: Topic :: Scientific/Engineering :: Information Analysis
Classifier: Topic :: Software Development :: Internationalization
Classifier: Topic :: Software Development :: Localization
Classifier: Topic :: Text Processing :: Linguistic
Classifier: Typing :: Typed
Requires-Python: >=3.8
License-File: LICENSE
Provides-Extra: marisa-trie
Requires-Dist: marisa_trie==1.2.0; extra == "marisa-trie"
Requires-Dist: platformdirs==4.2.2; extra == "marisa-trie"
Provides-Extra: test
Requires-Dist: pytest==8.3.2; extra == "test"
Requires-Dist: pytest-cov==5.0.0; extra == "test"
Provides-Extra: dev
Requires-Dist: simplemma[test]; extra == "dev"
Requires-Dist: black==24.8.0; extra == "dev"
Requires-Dist: flake8==7.1.1; extra == "dev"
Requires-Dist: mypy==1.11.0; extra == "dev"
Requires-Dist: types-requests==2.32.0.20240712; extra == "dev"
Provides-Extra: docs
Requires-Dist: mkdocs; extra == "docs"
Requires-Dist: mkdocs-material; extra == "docs"
Requires-Dist: mkdocstrings; extra == "docs"
Requires-Dist: mkdocstrings-python; extra == "docs"
